{
	"ulid": "01JWF50ST17VJYPT9BD11HS071",
	"minTime": 1747922330700,
	"maxTime": 1747965600000,
	"stats": {
		"numSamples": 9422557,
		"numSeries": 3174,
		"numChunks": 80363
	},
	"compaction": {
		"level": 3,
		"sources": [
			"01JVWEXXQ7PDRBCTZAGWKV0YVV",
			"01JVWF026V35KY6TGB8ZS4F6PE",
			"01JVWVT63M2BXZJ7ED2BJGS68S",
			"01JVX4CCBS7K13TJXGRDRXHVQD",
			"01JWEHDRDS0FP74P7RNJ17034H",
			"01JWEHDRNW69VXK60BRAN9ZRV1"
		],
		"parents": [
			{
				"ulid": "01JWEHDS0YC52BT5ZSBH8R2SSJ",
				"minTime": 1747922330700,
				"maxTime": 1747936800000
			},
			{
				"ulid": "01JWF50SBMJP46RWW45027VXRB",
				"minTime": 1747944825636,
				"maxTime": 1747958400000
			},
			{
				"ulid": "01JWEHDRNW69VXK60BRAN9ZRV1",
				"minTime": 1747958400021,
				"maxTime": 1747965600000
			}
		]
	},
	"version": 1
}